milea_licence/__init__.py
milea_licence/admin.py
milea_licence/apps.py
milea_licence/models.py
milea_licence/settings.py
milea_licence/tests.py
milea_licence/locale/de/LC_MESSAGES/django.mo
milea_licence/locale/de/LC_MESSAGES/django.po
milea_licence/migrations/0001_initial.py
milea_licence/migrations/__init__.py
milea_licence/migrations/__pycache__/0001_initial.cpython-311.pyc
milea_licence/migrations/__pycache__/__init__.cpython-311.pyc
milea_licence-0.1.1.dist-info/METADATA
milea_licence-0.1.1.dist-info/WHEEL
milea_licence-0.1.1.dist-info/top_level.txt
milea_licence-0.1.1.dist-info/RECORD
